<annotation>
	<folder>annotations</folder>
	<filename>4205.png</filename>
	<path>/home/aydin/rsnanet/label/annotations/4205.png</path>
	<source>
		<database>Unknown</database>
	</source>
	<size>
		<width>1092</width>
		<height>1349</height>
		<depth>1</depth>
	</size>
	<segmented>0</segmented>
	<object>
		<name>PIP</name>
		<pose>Unspecified</pose>
		<truncated>0</truncated>
		<difficult>0</difficult>
		<bndbox>
			<xmin>442</xmin>
			<ymin>263</ymin>
			<xmax>521</xmax>
			<ymax>358</ymax>
		</bndbox>
	</object>
	<object>
		<name>PIP</name>
		<pose>Unspecified</pose>
		<truncated>0</truncated>
		<difficult>0</difficult>
		<bndbox>
			<xmin>297</xmin>
			<ymin>343</ymin>
			<xmax>370</xmax>
			<ymax>432</ymax>
		</bndbox>
	</object>
	<object>
		<name>PIP</name>
		<pose>Unspecified</pose>
		<truncated>0</truncated>
		<difficult>0</difficult>
		<bndbox>
			<xmin>621</xmin>
			<ymin>297</ymin>
			<xmax>697</xmax>
			<ymax>386</ymax>
		</bndbox>
	</object>
	<object>
		<name>DIP</name>
		<pose>Unspecified</pose>
		<truncated>0</truncated>
		<difficult>0</difficult>
		<bndbox>
			<xmin>432</xmin>
			<ymin>156</ymin>
			<xmax>500</xmax>
			<ymax>237</ymax>
		</bndbox>
	</object>
	<object>
		<name>Wrist</name>
		<pose>Unspecified</pose>
		<truncated>0</truncated>
		<difficult>0</difficult>
		<bndbox>
			<xmin>384</xmin>
			<ymin>732</ymin>
			<xmax>712</xmax>
			<ymax>967</ymax>
		</bndbox>
	</object>
	<object>
		<name>DIP</name>
		<pose>Unspecified</pose>
		<truncated>0</truncated>
		<difficult>0</difficult>
		<bndbox>
			<xmin>645</xmin>
			<ymin>204</ymin>
			<xmax>707</xmax>
			<ymax>283</ymax>
		</bndbox>
	</object>
	<object>
		<name>MCP</name>
		<pose>Unspecified</pose>
		<truncated>0</truncated>
		<difficult>0</difficult>
		<bndbox>
			<xmin>301</xmin>
			<ymin>570</ymin>
			<xmax>387</xmax>
			<ymax>669</ymax>
		</bndbox>
	</object>
	<object>
		<name>DIP</name>
		<pose>Unspecified</pose>
		<truncated>0</truncated>
		<difficult>0</difficult>
		<bndbox>
			<xmin>256</xmin>
			<ymin>239</ymin>
			<xmax>327</xmax>
			<ymax>324</ymax>
		</bndbox>
	</object>
	<object>
		<name>MCP</name>
		<pose>Unspecified</pose>
		<truncated>0</truncated>
		<difficult>0</difficult>
		<bndbox>
			<xmin>742</xmin>
			<ymin>628</ymin>
			<xmax>842</xmax>
			<ymax>730</ymax>
		</bndbox>
	</object>
	<object>
		<name>MCP</name>
		<pose>Unspecified</pose>
		<truncated>0</truncated>
		<difficult>0</difficult>
		<bndbox>
			<xmin>369</xmin>
			<ymin>503</ymin>
			<xmax>459</xmax>
			<ymax>609</ymax>
		</bndbox>
	</object>
	<object>
		<name>PIP</name>
		<pose>Unspecified</pose>
		<truncated>0</truncated>
		<difficult>0</difficult>
		<bndbox>
			<xmin>819</xmin>
			<ymin>511</ymin>
			<xmax>908</xmax>
			<ymax>614</ymax>
		</bndbox>
	</object>
	<object>
		<name>MCP</name>
		<pose>Unspecified</pose>
		<truncated>0</truncated>
		<difficult>0</difficult>
		<bndbox>
			<xmin>459</xmin>
			<ymin>456</ymin>
			<xmax>555</xmax>
			<ymax>567</ymax>
		</bndbox>
	</object>
	<object>
		<name>MCP</name>
		<pose>Unspecified</pose>
		<truncated>0</truncated>
		<difficult>0</difficult>
		<bndbox>
			<xmin>563</xmin>
			<ymin>455</ymin>
			<xmax>667</xmax>
			<ymax>572</ymax>
		</bndbox>
	</object>
	<object>
		<name>Ulna</name>
		<pose>Unspecified</pose>
		<truncated>0</truncated>
		<difficult>0</difficult>
		<bndbox>
			<xmin>391</xmin>
			<ymin>926</ymin>
			<xmax>489</xmax>
			<ymax>1026</ymax>
		</bndbox>
	</object>
	<object>
		<name>DIP</name>
		<pose>Unspecified</pose>
		<truncated>0</truncated>
		<difficult>0</difficult>
		<bndbox>
			<xmin>143</xmin>
			<ymin>418</ymin>
			<xmax>215</xmax>
			<ymax>507</ymax>
		</bndbox>
	</object>
	<object>
		<name>PIP</name>
		<pose>Unspecified</pose>
		<truncated>0</truncated>
		<difficult>0</difficult>
		<bndbox>
			<xmin>204</xmin>
			<ymin>478</ymin>
			<xmax>272</xmax>
			<ymax>570</ymax>
		</bndbox>
	</object>
	<object>
		<name>Radius</name>
		<pose>Unspecified</pose>
		<truncated>0</truncated>
		<difficult>0</difficult>
		<bndbox>
			<xmin>475</xmin>
			<ymin>913</ymin>
			<xmax>631</xmax>
			<ymax>1031</ymax>
		</bndbox>
	</object>
</annotation>
